{
  "project_info": {
    "project_number": "155467344487",
    "project_id": "burger-restaurant-app",
    "storage_bucket": "burger-restaurant-app.firebasestorage.app"
  },
  "client": [
    {
      "client_info": {
        "mobilesdk_app_id": "1:155467344487:android:12ea7e22ddb37b221cc2c2",
        "android_client_info": {
          "package_name": "com.stephennnamani.burgerrestaurantapp"
        }
      },
      "oauth_client": [
        {
          "client_id": "155467344487-3fgqar1nmtil4c5ra2hl6ubvsglg69sm.apps.googleusercontent.com",
          "client_type": 1,
          "android_info": {
            "package_name": "com.stephennnamani.burgerrestaurantapp",
            "certificate_hash": "8e87074833953c66d224576c9e7825da18850a0f"
          }
        },
        {
          "client_id": "155467344487-vkoqk4d77sod098qd1r3m08takdbltl6.apps.googleusercontent.com",
          "client_type": 1,
          "android_info": {
            "package_name": "com.stephennnamani.burgerrestaurantapp",
            "certificate_hash": "c42aea6627fbb2febb0be211ac3c9a45030c1b04"
          }
        },
        {
          "client_id": "155467344487-a8u99jb9nu8rucpcqh7sobkika7j4tda.apps.googleusercontent.com",
          "client_type": 3
        }
      ],
      "api_key": [
        {
          "current_key": "AIzaSyAJ9JrPEFyWjcMVLlbcZOT4pFJfjK-_m6w"
        }
      ],
      "services": {
        "appinvite_service": {
          "other_platform_oauth_client": [
            {
              "client_id": "155467344487-a8u99jb9nu8rucpcqh7sobkika7j4tda.apps.googleusercontent.com",
              "client_type": 3
            }
          ]
        }
      }
    }
  ],
  "configuration_version": "1"
}